saucenao/__init__.py
saucenao/__version__.py
saucenao/exceptions.py
saucenao/http.py
saucenao/saucenao.py
saucenao/worker.py
saucenao/files/__init__.py
saucenao/files/constraint.py
saucenao/files/filehandler.py
saucenao/files/filter.py
tests/__init__.py
tests/test_http.py
tests/test_init.py
tests/test_saucenao.py
tests/test_version.py
tests/test_worker.py
tests/custom/__init__.py
tests/custom/test_saucenao_limit.py
tests/files/__init__.py
tests/files/test_constraint.py
tests/files/test_filehandler.py
tests/files/test_filter.py
SauceNAO-1.1.0.dist-info/LICENSE
SauceNAO-1.1.0.dist-info/METADATA
SauceNAO-1.1.0.dist-info/WHEEL
SauceNAO-1.1.0.dist-info/top_level.txt
SauceNAO-1.1.0.dist-info/zip-safe
SauceNAO-1.1.0.dist-info/RECORD
