Metadata-Version: 2.1
Name: SauceNAO
Version: 1.1.0
Summary: Small module to work with SauceNAO locally
Home-page: https://github.com/DaRealFreak/saucenao
Author: DaRealFreak
Author-email: steffen.keuper@web.de
License: MIT
Platform: UNKNOWN
Requires-Dist: bs4 (>=0.0.1)
Requires-Dist: requests (>=2.18.4)
Provides-Extra: dev
Requires-Dist: python-dotenv (>=0.7.1) ; extra == 'dev'
Requires-Dist: Pillow (>=5.0.0) ; extra == 'dev'
Requires-Dist: requests-mock (>=1.4.0) ; extra == 'dev'
Requires-Dist: nose-exclude (>=0.5.0) ; extra == 'dev'
Requires-Dist: coveralls (>=1.10.0) ; extra == 'dev'
Provides-Extra: titlesearch
Requires-Dist: titlesearch (>=0.0.1) ; extra == 'titlesearch'
